numpythia/__init__.py
numpythia/_libnumpythia.cpython-36m-x86_64-linux-gnu.so
numpythia/testcmnd/w.cmnd
numpythia/testcmnd/__init__.py
numpythia/testcmnd/qcd.cmnd
numpythia/testcmnd/pileup.cmnd
numpythia/src/extern/pythia8244/share/Pythia8/xmldoc/SaveSettings.xml
numpythia/src/extern/pythia8244/share/Pythia8/xmldoc/SampleMainPrograms.xml
numpythia/src/extern/pythia8244/share/Pythia8/xmldoc/HeavyIons.xml
numpythia/src/extern/pythia8244/share/Pythia8/xmldoc/pomactwd14.pds
numpythia/src/extern/pythia8244/share/Pythia8/xmldoc/DeuteronProduction.xml
numpythia/src/extern/pythia8244/share/Pythia8/xmldoc/LeftRightSymmetryProcesses.xml
numpythia/src/extern/pythia8244/share/Pythia8/xmldoc/pomH1FitBlo.data
numpythia/src/extern/pythia8244/share/Pythia8/xmldoc/FourthGenerationProcesses.xml
numpythia/src/extern/pythia8244/share/Pythia8/xmldoc/Welcome.xml
numpythia/src/extern/pythia8244/share/Pythia8/xmldoc/AdvancedUsage.xml
numpythia/src/extern/pythia8244/share/Pythia8/xmldoc/NNPDF31_lo_as_0130_0000.dat
numpythia/src/extern/pythia8244/share/Pythia8/xmldoc/CompositenessProcesses.xml
numpythia/src/extern/pythia8244/share/Pythia8/xmldoc/GKG18_DPDF_FitB_LO_0000.dat
numpythia/src/extern/pythia8244/share/Pythia8/xmldoc/RIVETusage.xml
numpythia/src/extern/pythia8244/share/Pythia8/xmldoc/JetMatching.xml
numpythia/src/extern/pythia8244/share/Pythia8/xmldoc/Fragmentation.xml
numpythia/src/extern/pythia8244/share/Pythia8/xmldoc/Tunes.xml
numpythia/src/extern/pythia8244/share/Pythia8/xmldoc/UMEPSMerging.xml
numpythia/src/extern/pythia8244/share/Pythia8/xmldoc/MultipartonInteractions.xml
numpythia/src/extern/pythia8244/share/Pythia8/xmldoc/Version.xml
numpythia/src/extern/pythia8244/share/Pythia8/xmldoc/ElectroweakProcesses.xml
numpythia/src/extern/pythia8244/share/Pythia8/xmldoc/GKG18_DPDF_FitA_LO_0000.dat
numpythia/src/extern/pythia8244/share/Pythia8/xmldoc/pipi-Froggatt.dat
numpythia/src/extern/pythia8244/share/Pythia8/xmldoc/MainProgramSettings.xml
numpythia-1.2.0.dist-info/WHEEL
numpythia-1.2.0.dist-info/RECORD
numpythia-1.2.0.dist-info/top_level.txt
numpythia-1.2.0.dist-info/METADATA
numpythia-1.2.0.dist-info/COPYING
